collective.volto.sitesettings-1.0.6-py3.10-nspkg.pth
collective/volto/sitesettings/__init__.py
collective/volto/sitesettings/configure.zcml
collective/volto/sitesettings/interfaces.py
collective/volto/sitesettings/setuphandlers.py
collective/volto/sitesettings/testing.py
collective/volto/sitesettings/utils.py
collective/volto/sitesettings/browser/__init__.py
collective/volto/sitesettings/browser/configure.zcml
collective/volto/sitesettings/browser/site_helpers_views.py
collective/volto/sitesettings/browser/overrides/.gitkeep
collective/volto/sitesettings/browser/static/.gitkeep
collective/volto/sitesettings/locales/README.rst
collective/volto/sitesettings/locales/__init__.py
collective/volto/sitesettings/locales/collective.volto.sitesettings.pot
collective/volto/sitesettings/locales/update.py
collective/volto/sitesettings/locales/update.sh
collective/volto/sitesettings/locales/it/LC_MESSAGES/collective.volto.sitesettings.mo
collective/volto/sitesettings/locales/it/LC_MESSAGES/collective.volto.sitesettings.po
collective/volto/sitesettings/profiles/default/browserlayer.xml
collective/volto/sitesettings/profiles/default/catalog.xml
collective/volto/sitesettings/profiles/default/metadata.xml
collective/volto/sitesettings/profiles/default/rolemap.xml
collective/volto/sitesettings/profiles/default/registry/main.xml
collective/volto/sitesettings/profiles/uninstall/browserlayer.xml
collective/volto/sitesettings/profiles/uninstall/registry.xml
collective/volto/sitesettings/restapi/__init__.py
collective/volto/sitesettings/restapi/configure.zcml
collective/volto/sitesettings/restapi/controlpanels/__init__.py
collective/volto/sitesettings/restapi/controlpanels/configure.zcml
collective/volto/sitesettings/restapi/controlpanels/site.py
collective/volto/sitesettings/restapi/deserializer/__init__.py
collective/volto/sitesettings/restapi/deserializer/configure.zcml
collective/volto/sitesettings/restapi/deserializer/controlpanels.py
collective.volto.sitesettings-1.0.6.dist-info/LICENSE.GPL
collective.volto.sitesettings-1.0.6.dist-info/LICENSE.rst
collective.volto.sitesettings-1.0.6.dist-info/METADATA
collective.volto.sitesettings-1.0.6.dist-info/WHEEL
collective.volto.sitesettings-1.0.6.dist-info/entry_points.txt
collective.volto.sitesettings-1.0.6.dist-info/namespace_packages.txt
collective.volto.sitesettings-1.0.6.dist-info/top_level.txt
collective.volto.sitesettings-1.0.6.dist-info/RECORD
