Metadata-Version: 2.1
Name: collective.volto.sitesettings
Version: 1.0.6
Summary: Plone addon to allow to extend @site controlpanel
Home-page: https://github.com/collective/collective.volto.sitesettings
Author: RedTurtle Technology
Author-email: sviluppo@redturtle.it
License: GPL version 2
Project-URL: PyPI, https://pypi.org/project/collective.volto.sitesettings/
Project-URL: Source, https://github.com/collective/collective.volto.sitesettings
Project-URL: Tracker, https://github.com/collective/collective.volto.sitesettings/issues
Keywords: Python Plone CMS
Classifier: Development Status :: 5 - Production/Stable
Classifier: Environment :: Web Environment
Classifier: Framework :: Plone
Classifier: Framework :: Plone :: Addon
Classifier: Framework :: Plone :: 5.2
Classifier: Framework :: Plone :: 6.0
Classifier: Programming Language :: Python
Classifier: Programming Language :: Python :: 3.7
Classifier: Programming Language :: Python :: 3.8
Classifier: Programming Language :: Python :: 3.9
Classifier: Operating System :: OS Independent
Classifier: License :: OSI Approved :: GNU General Public License v2 (GPLv2)
Requires-Python: >=3.7
License-File: LICENSE.GPL
License-File: LICENSE.rst
Requires-Dist: setuptools
Requires-Dist: Plone
Provides-Extra: test
Requires-Dist: plone.app.testing ; extra == 'test'
Requires-Dist: plone.restapi[test] ; extra == 'test'
